pysendgmaillib/__init__.py
pysendgmaillib/pysendgmaillib.py
pysendgmaillib-1.1.1.dist-info/DESCRIPTION.rst
pysendgmaillib-1.1.1.dist-info/METADATA
pysendgmaillib-1.1.1.dist-info/RECORD
pysendgmaillib-1.1.1.dist-info/WHEEL
pysendgmaillib-1.1.1.dist-info/metadata.json
pysendgmaillib-1.1.1.dist-info/top_level.txt
