Metadata-Version: 2.0
Name: pysendgmaillib
Version: 1.1.1
Summary: Python Gmail sending library
Home-page: UNKNOWN
Author: Kaiwen Wu
Author-email: kps6326@hotmail.com
License: UNKNOWN
Platform: UNKNOWN
